{
	"class" : {
		 },
	"instance" : {
		"anyAuthenticatedConnection" : "HolgerHansPeterFreyther 8/22/2014 20:25",
		"connect" : "HolgerHansPeterFreyther 8/29/2014 15:08",
		"createConnection:port:" : "HolgerHansPeterFreyther 8/29/2014 14:28",
		"dispatchMessage:" : "HolgerHansPeterFreyther 7/28/2014 14:13",
		"dispatchOne" : "HolgerHansPeterFreyther 8/29/2014 15:03",
		"initialize" : "HolgerHansPeterFreyther 8/29/2014 15:35",
		"initializeConnection" : "HolgerHansPeterFreyther 8/29/2014 15:06",
		"onUnhandledCommandOrResponse:" : "HolgerHansPeterFreyther 8/29/2014 15:04",
		"onUnhandledResponse:" : "HolgerHansPeterFreyther 8/29/2014 15:05",
		"password:" : "HolgerHansPeterFreyther 8/29/2014 15:05",
		"sendDirect:" : "HolgerHansPeterFreyther 8/22/2014 20:03",
		"sendOne" : "HolgerHansPeterFreyther 8/27/2014 07:00",
		"systemId:" : "HolgerHansPeterFreyther 8/29/2014 15:10",
		"systemType:" : "HolgerHansPeterFreyther 8/29/2014 15:11" } }
